{
  "id": "bf40d029-e6bc-4e9d-85ac-ef40a498b1ba",
  "prevId": "9608f70e-c24a-4c0e-9583-250a06408ee3",
  "version": "7",
  "dialect": "postgresql",
  "tables": {
    "public.registered_users": {
      "name": "registered_users",
      "schema": "",
      "columns": {
        "id": {
          "name": "id",
          "type": "serial",
          "primaryKey": true,
          "notNull": true
        },
        "slots": {
          "name": "slots",
          "type": "integer[]",
          "primaryKey": false,
          "notNull": false
        },
        "name": {
          "name": "name",
          "type": "text",
          "primaryKey": false,
          "notNull": false
        },
        "age": {
          "name": "age",
          "type": "integer",
          "primaryKey": false,
          "notNull": false
        },
        "email": {
          "name": "email",
          "type": "text",
          "primaryKey": false,
          "notNull": false
        },
        "phone_no": {
          "name": "phone_no",
          "type": "text",
          "primaryKey": false,
          "notNull": false
        },
        "topUpCredit": {
          "name": "topUpCredit",
          "type": "integer",
          "primaryKey": false,
          "notNull": false
        },
        "chakra": {
          "name": "chakra",
          "type": "text",
          "primaryKey": false,
          "notNull": false
        },
        "lang_used": {
          "name": "lang_used",
          "type": "text",
          "primaryKey": false,
          "notNull": false
        },
        "created_at": {
          "name": "created_at",
          "type": "date",
          "primaryKey": false,
          "notNull": true,
          "default": "now()"
        },
        "registration_fees": {
          "name": "registration_fees",
          "type": "integer",
          "primaryKey": false,
          "notNull": false
        },
        "total_amt": {
          "name": "total_amt",
          "type": "integer",
          "primaryKey": false,
          "notNull": false
        },
        "volunteer": {
          "name": "volunteer",
          "type": "text",
          "primaryKey": false,
          "notNull": false
        },
        "status": {
          "name": "status",
          "type": "text",
          "primaryKey": false,
          "notNull": false,
          "default": "'registered'"
        },
        "code": {
          "name": "code",
          "type": "text",
          "primaryKey": false,
          "notNull": false
        },
        "sevaka_type": {
          "name": "sevaka_type",
          "type": "text",
          "primaryKey": false,
          "notNull": false
        },
        "sevaka_slots": {
          "name": "sevaka_slots",
          "type": "integer[]",
          "primaryKey": false,
          "notNull": false
        }
      },
      "indexes": {},
      "foreignKeys": {},
      "compositePrimaryKeys": {},
      "uniqueConstraints": {},
      "policies": {},
      "checkConstraints": {},
      "isRLSEnabled": false
    },
    "public.todo": {
      "name": "todo",
      "schema": "",
      "columns": {
        "id": {
          "name": "id",
          "type": "integer",
          "primaryKey": true,
          "notNull": true
        },
        "text": {
          "name": "text",
          "type": "text",
          "primaryKey": false,
          "notNull": true
        },
        "done": {
          "name": "done",
          "type": "boolean",
          "primaryKey": false,
          "notNull": true,
          "default": false
        }
      },
      "indexes": {},
      "foreignKeys": {},
      "compositePrimaryKeys": {},
      "uniqueConstraints": {},
      "policies": {},
      "checkConstraints": {},
      "isRLSEnabled": false
    }
  },
  "enums": {},
  "schemas": {},
  "sequences": {},
  "roles": {},
  "policies": {},
  "views": {},
  "_meta": {
    "columns": {},
    "schemas": {},
    "tables": {}
  }
}